future_uuid.py
future_uuid-1.0.0.dist-info/licenses/LICENSE
future_uuid-1.0.0.dist-info/METADATA
future_uuid-1.0.0.dist-info/WHEEL
future_uuid-1.0.0.dist-info/top_level.txt
future_uuid-1.0.0.dist-info/RECORD
