Metadata-Version: 2.4
Name: future-uuid
Version: 1.0.0
Summary: A backport of Python3.14's UUID6, UUID7 and UUID8 implementations to 3.9+
Author: Rasmus Nygren
License: MIT License
Project-URL: Homepage, https://github.com/rasmusnygren/future-uuid
Classifier: Development Status :: 3 - Alpha
Classifier: Intended Audience :: Developers
Classifier: License :: OSI Approved :: MIT License
Classifier: Programming Language :: Python :: 3
Classifier: Programming Language :: Python :: 3.9
Classifier: Programming Language :: Python :: 3.10
Classifier: Programming Language :: Python :: 3.11
Classifier: Programming Language :: Python :: 3.12
Classifier: Programming Language :: Python :: 3.13
Requires-Python: >=3.9
License-File: LICENSE
Dynamic: license-file
